ssspy/__init__.py
ssspy/_version.py
ssspy/algorithm/__init__.py
ssspy/algorithm/minimal_distortion_principle.py
ssspy/algorithm/permutation_alignment.py
ssspy/algorithm/projection_back.py
ssspy/bss/__init__.py
ssspy/bss/_flooring.py
ssspy/bss/_psd.py
ssspy/bss/_select_pair.py
ssspy/bss/_solve_permutation.py
ssspy/bss/_update_spatial_model.py
ssspy/bss/admmbss.py
ssspy/bss/base.py
ssspy/bss/cacgmm.py
ssspy/bss/fdica.py
ssspy/bss/hva.py
ssspy/bss/ica.py
ssspy/bss/ilrma.py
ssspy/bss/ipsdta.py
ssspy/bss/iva.py
ssspy/bss/mnmf.py
ssspy/bss/pdsbss.py
ssspy/bss/proxbss.py
ssspy/io/__init__.py
ssspy/linalg/__init__.py
ssspy/linalg/_solve.py
ssspy/linalg/cubic.py
ssspy/linalg/eigh.py
ssspy/linalg/inv.py
ssspy/linalg/lqpqm.py
ssspy/linalg/mean.py
ssspy/linalg/polynomial.py
ssspy/linalg/prox.py
ssspy/linalg/quadratic.py
ssspy/linalg/sqrtm.py
ssspy/special/__init__.py
ssspy/special/flooring.py
ssspy/special/logsumexp.py
ssspy/special/psd.py
ssspy/special/softmax.py
ssspy/transform/__init__.py
ssspy/transform/pca.py
ssspy/transform/whiten.py
ssspy/utils/__init__.py
ssspy/utils/flooring.py
ssspy/utils/select_pair.py
ssspy/utils/dataset/__init__.py
ssspy/utils/dataset/mird.py
ssspy/utils/dataset/sisec2010.py
ssspy-0.2.0.dist-info/licenses/LICENSE
ssspy-0.2.0.dist-info/METADATA
ssspy-0.2.0.dist-info/WHEEL
ssspy-0.2.0.dist-info/top_level.txt
ssspy-0.2.0.dist-info/RECORD
