Metadata-Version: 2.4
Name: ssspy
Version: 0.2.0
Summary: A Python toolkit for sound source separation.
Author: Takuya Hasumi
License:                                  Apache License
Project-URL: url, https://github.com/tky823/ssspy
Requires-Python: <4,>=3.8
License-File: LICENSE
Requires-Dist: numpy
Provides-Extra: dev
Requires-Dist: flake8; extra == "dev"
Requires-Dist: black; extra == "dev"
Requires-Dist: isort; extra == "dev"
Provides-Extra: docs
Requires-Dist: sphinx; extra == "docs"
Requires-Dist: sphinx-autodoc-typehints; extra == "docs"
Requires-Dist: sphinx-autobuild; extra == "docs"
Requires-Dist: nbsphinx; extra == "docs"
Requires-Dist: furo; extra == "docs"
Provides-Extra: notebooks
Requires-Dist: ipykernel; extra == "notebooks"
Requires-Dist: matplotlib; extra == "notebooks"
Requires-Dist: scipy; extra == "notebooks"
Provides-Extra: tests
Requires-Dist: pytest; extra == "tests"
Requires-Dist: pytest-cov; extra == "tests"
Requires-Dist: pytest-xdist; extra == "tests"
Requires-Dist: scipy; extra == "tests"
Dynamic: license-file
